ideo/__init__.py
ideo/__main__.py
ideo/ideo.py
ideo-0.2.1.dist-info/LICENSE
ideo-0.2.1.dist-info/METADATA
ideo-0.2.1.dist-info/WHEEL
ideo-0.2.1.dist-info/entry_points.txt
ideo-0.2.1.dist-info/top_level.txt
ideo-0.2.1.dist-info/RECORD
