Metadata-Version: 2.1
Name: ideo
Version: 0.2.1
Summary: High quality image generation by ideogram.ai. Reverse engineered API.
Home-page: https://github.com/yihong0618/IdeoImageCreator
Author: yihong0618
Project-URL: Bug Report, https://github.com/yihong0618/IdeoImageCreator/issues/new
Classifier: Intended Audience :: Developers
Classifier: Topic :: Software Development :: Libraries :: Python Modules
Classifier: Programming Language :: Python :: 3.8
Classifier: Programming Language :: Python :: 3.9
Classifier: Programming Language :: Python :: 3.10
Classifier: Programming Language :: Python :: 3.11
License-File: LICENSE
Requires-Dist: curl-cffi
Requires-Dist: requests
Requires-Dist: fake-useragent
